dev_assistant_client/__init__.py
dev_assistant_client/ably_handler.py
dev_assistant_client/api_client.py
dev_assistant_client/cli.py
dev_assistant_client/client.py
dev_assistant_client/client_auth.py
dev_assistant_client/config.py
dev_assistant_client/dev_assistant_client.py
dev_assistant_client/icon.ico
dev_assistant_client/io.py
dev_assistant_client/modules/files.py
dev_assistant_client/modules/files_test.py
dev_assistant_client/modules/git.py
dev_assistant_client/modules/terminal.py
dev_assistant_client/utils.py
dev_assistant_client-0.2.51.dist-info/LICENSE
dev_assistant_client-0.2.51.dist-info/METADATA
dev_assistant_client-0.2.51.dist-info/WHEEL
dev_assistant_client-0.2.51.dist-info/entry_points.txt
dev_assistant_client-0.2.51.dist-info/RECORD
