Metadata-Version: 2.1
Name: dev-assistant-client
Version: 0.2.51
Summary: Dev Assistant client
Author: Luciano T.
Author-email: tonetlds@gmail.com
Requires-Python: >=3.8,<3.13
Classifier: Programming Language :: Python :: 3
Classifier: Programming Language :: Python :: 3.8
Classifier: Programming Language :: Python :: 3.9
Classifier: Programming Language :: Python :: 3.10
Classifier: Programming Language :: Python :: 3.11
Classifier: Programming Language :: Python :: 3.12
Requires-Dist: ably (>=2.0.6,<3.0.0)
Requires-Dist: appdirs (>=1.4.4,<2.0.0)
Requires-Dist: asyncio (>=3.4.3,<4.0.0)
Requires-Dist: colorama (>=0.4.6,<0.5.0)
Requires-Dist: gitpython (>=3.1.40,<4.0.0)
Requires-Dist: inquirer (>=3.1.4,<4.0.0)
Requires-Dist: packaging (>=23.2,<24.0)
Requires-Dist: plyer (>=2.1.0,<3.0.0)
Requires-Dist: pusher (>=3.3.2,<4.0.0)
Requires-Dist: pyinstaller (>=6.3.0,<7.0.0)
Requires-Dist: pystray (>=0.19.5,<0.20.0)
Requires-Dist: python-dotenv (>=1.0.0,<2.0.0)
Requires-Dist: requests (>=2.31.0,<3.0.0)
Requires-Dist: rich (>=13.7.0,<14.0.0)
Requires-Dist: tabulate (>=0.9.0,<0.10.0)
Requires-Dist: toml (>=0.10.2,<0.11.0)
Requires-Dist: unidiff (>=0.7.5,<0.8.0)
